{"4cb54d076e89f635722e":{"id":"4cb54d076e89f635722e","singleCourseJsons":[{"phase":"Prima Graduatoria Di Seconda Fase","school":"Ingegneria","year":2022,"url":{"pageEnum":1,"url":"http://www.risultati-ammissione.polimi.it/2022_20064_html/2022_20064_generale.html"},"course":"INGEGNERIA GESTIONALE"},{"phase":"Prima Graduatoria Di Seconda Fase","school":"Ingegneria","year":2022,"url":{"pageEnum":1,"url":"http://www.risultati-ammissione.polimi.it\\2022_20064_html\\2022_20064_generale.html"},"course":"INGEGNERIA GESTIONALE"}],"rankingSummaries":[{"phase":"Prima Graduatoria Di Seconda Fase","school":"Ingegneria","year":2022,"url":{"pageEnum":1,"url":"http://www.risultati-ammissione.polimi.it/2022_20064_html/2022_20064_generale.html"},"course":null},{"phase":"Prima Graduatoria Di Seconda Fase","school":"Ingegneria","year":2022,"url":{"pageEnum":1,"url":"http://www.risultati-ammissione.polimi.it/2022_20064_html/2022_20064_generale.html"},"course":null},{"phase":"Prima Graduatoria Di Seconda Fase","school":"Ingegneria","year":2022,"url":{"pageEnum":1,"url":"http://www.risultati-ammissione.polimi.it\\2022_20064_html\\2022_20064_generale.html"},"course":null},{"phase":"Prima Graduatoria Di Seconda Fase","school":"Ingegneria","year":2022,"url":{"pageEnum":1,"url":"http://www.risultati-ammissione.polimi.it\\2022_20064_html\\2022_20064_generale.html"},"course":null}],"inMeritTable":true},"4cb5033dc8f2afda1fd1":{"id":"4cb5033dc8f2afda1fd1","singleCourseJsons":[{"phase":"Prima Graduatoria Di Seconda Fase","school":"Ingegneria","year":2022,"url":{"pageEnum":1,"url":"http://www.risultati-ammissione.polimi.it/2022_20064_html/2022_20064_generale.html"},"course":"INGEGNERIA CHIMICA"},{"phase":"Prima Graduatoria Di Seconda Fase","school":"Ingegneria","year":2022,"url":{"pageEnum":1,"url":"http://www.risultati-ammissione.polimi.it/2022_20064_html/2022_20064_generale.html"},"course":"INGEGNERIA MECCANICA"},{"phase":"Prima Graduatoria Di Seconda Fase","school":"Ingegneria","year":2022,"url":{"pageEnum":1,"url":"http://www.risultati-ammissione.polimi.it\\2022_20064_html\\2022_20064_generale.html"},"course":"INGEGNERIA CHIMICA"},{"phase":"Prima Graduatoria Di Seconda Fase","school":"Ingegneria","year":2022,"url":{"pageEnum":1,"url":"http://www.risultati-ammissione.polimi.it\\2022_20064_html\\2022_20064_generale.html"},"course":"INGEGNERIA MECCANICA"}],"rankingSummaries":[{"phase":"Prima Graduatoria Di Seconda Fase","school":"Ingegneria","year":2022,"url":{"pageEnum":1,"url":"http://www.risultati-ammissione.polimi.it/2022_20064_html/2022_20064_generale.html"},"course":null},{"phase":"Prima Graduatoria Di Seconda Fase","school":"Ingegneria","year":2022,"url":{"pageEnum":1,"url":"http://www.risultati-ammissione.polimi.it/2022_20064_html/2022_20064_generale.html"},"course":null},{"phase":"Prima Graduatoria Di Seconda Fase","school":"Ingegneria","year":2022,"url":{"pageEnum":1,"url":"http://www.risultati-ammissione.polimi.it/2022_20064_html/2022_20064_generale.html"},"course":null},{"phase":"Prima Graduatoria Di Seconda Fase","school":"Ingegneria","year":2022,"url":{"pageEnum":1,"url":"http://www.risultati-ammissione.polimi.it\\2022_20064_html\\2022_20064_generale.html"},"course":null},{"phase":"Prima Graduatoria Di Seconda Fase","school":"Ingegneria","year":2022,"url":{"pageEnum":1,"url":"http://www.risultati-ammissione.polimi.it\\2022_20064_html\\2022_20064_generale.html"},"course":null},{"phase":"Prima Graduatoria Di Seconda Fase","school":"Ingegneria","year":2022,"url":{"pageEnum":1,"url":"http://www.risultati-ammissione.polimi.it\\2022_20064_html\\2022_20064_generale.html"},"course":null}],"inMeritTable":true}}