{"575b15d68fa17a8ad271":{"id":"575b15d68fa17a8ad271","singleCourseJsons":[{"phase":"Anticipata","school":"Urbanistica","year":2023,"url":{"pageEnum":1,"url":"http://www.risultati-ammissione.polimi.it/2023_20008_5b48_html/2023_20008_generale.html"},"course":"URBANISTICA: CITTA' AMBIENTE PAESAGGIO"},{"phase":"Anticipata","school":"Urbanistica","year":2023,"url":{"pageEnum":1,"url":"http://www.risultati-ammissione.polimi.it\\2023_20008_5b48_html\\2023_20008_generale.html"},"course":"URBANISTICA: CITTA' AMBIENTE PAESAGGIO"}],"rankingSummaries":[{"phase":"Anticipata","school":"Urbanistica","year":2023,"url":{"pageEnum":1,"url":"http://www.risultati-ammissione.polimi.it/2023_20008_5b48_html/2023_20008_generale.html"},"course":null},{"phase":"Anticipata","school":"Urbanistica","year":2023,"url":{"pageEnum":1,"url":"http://www.risultati-ammissione.polimi.it/2023_20008_5b48_html/2023_20008_generale.html"},"course":null},{"phase":"Anticipata","school":"Urbanistica","year":2023,"url":{"pageEnum":1,"url":"http://www.risultati-ammissione.polimi.it\\2023_20008_5b48_html\\2023_20008_generale.html"},"course":null},{"phase":"Anticipata","school":"Urbanistica","year":2023,"url":{"pageEnum":1,"url":"http://www.risultati-ammissione.polimi.it\\2023_20008_5b48_html\\2023_20008_generale.html"},"course":null}],"inMeritTable":true},"575b31b87cc3039b5aeb":{"id":"575b31b87cc3039b5aeb","singleCourseJsons":[{"phase":"Prima Graduatoria","school":"Architettura","year":2021,"url":{"pageEnum":1,"url":"http://www.risultati-ammissione.polimi.it/2021_20002_html/2021_20002_generale.html"},"course":"PROGETTAZIONE DELL'ARCHITETTURA"},{"phase":"Prima Graduatoria","school":"Architettura","year":2021,"url":{"pageEnum":1,"url":"http://www.risultati-ammissione.polimi.it\\2021_20002_html\\2021_20002_generale.html"},"course":"PROGETTAZIONE DELL'ARCHITETTURA"}],"rankingSummaries":[{"phase":"Prima Graduatoria","school":"Architettura","year":2021,"url":{"pageEnum":1,"url":"http://www.risultati-ammissione.polimi.it/2021_20002_html/2021_20002_generale.html"},"course":null},{"phase":"Prima Graduatoria","school":"Architettura","year":2021,"url":{"pageEnum":1,"url":"http://www.risultati-ammissione.polimi.it/2021_20002_html/2021_20002_generale.html"},"course":null},{"phase":"Prima Graduatoria","school":"Architettura","year":2021,"url":{"pageEnum":1,"url":"http://www.risultati-ammissione.polimi.it\\2021_20002_html\\2021_20002_generale.html"},"course":null},{"phase":"Prima Graduatoria","school":"Architettura","year":2021,"url":{"pageEnum":1,"url":"http://www.risultati-ammissione.polimi.it\\2021_20002_html\\2021_20002_generale.html"},"course":null}],"inMeritTable":true}}