{"6b5e7de8c4f63a2f7618":{"id":"6b5e7de8c4f63a2f7618","singleCourseJsons":[{"phase":"Prima Graduatoria Di Seconda Fase","school":"Ingegneria","year":2022,"url":{"pageEnum":1,"url":"http://www.risultati-ammissione.polimi.it/2022_20064_html/2022_20064_generale.html"},"course":"INGEGNERIA GESTIONALE"},{"phase":"Prima Graduatoria Di Seconda Fase","school":"Ingegneria","year":2022,"url":{"pageEnum":1,"url":"http://www.risultati-ammissione.polimi.it\\2022_20064_html\\2022_20064_generale.html"},"course":"INGEGNERIA GESTIONALE"}],"rankingSummaries":[{"phase":"Prima Graduatoria Di Seconda Fase","school":"Ingegneria","year":2022,"url":{"pageEnum":1,"url":"http://www.risultati-ammissione.polimi.it/2022_20064_html/2022_20064_generale.html"},"course":null},{"phase":"Prima Graduatoria Di Seconda Fase","school":"Ingegneria","year":2022,"url":{"pageEnum":1,"url":"http://www.risultati-ammissione.polimi.it/2022_20064_html/2022_20064_generale.html"},"course":null},{"phase":"Prima Graduatoria Di Seconda Fase","school":"Ingegneria","year":2022,"url":{"pageEnum":1,"url":"http://www.risultati-ammissione.polimi.it\\2022_20064_html\\2022_20064_generale.html"},"course":null},{"phase":"Prima Graduatoria Di Seconda Fase","school":"Ingegneria","year":2022,"url":{"pageEnum":1,"url":"http://www.risultati-ammissione.polimi.it\\2022_20064_html\\2022_20064_generale.html"},"course":null}],"inMeritTable":true},"6b5e18211ef8b2cc92fe":{"id":"6b5e18211ef8b2cc92fe","singleCourseJsons":[{"phase":"Anticipato","school":"Design","year":2022,"url":{"pageEnum":1,"url":"http://www.risultati-ammissione.polimi.it/2022_20040_html/2022_20040_generale.html"},"course":"DESIGN DEGLI INTERNI"},{"phase":"Anticipato","school":"Design","year":2022,"url":{"pageEnum":1,"url":"http://www.risultati-ammissione.polimi.it\\2022_20040_html\\2022_20040_generale.html"},"course":"DESIGN DEGLI INTERNI"}],"rankingSummaries":[{"phase":"Anticipato","school":"Design","year":2022,"url":{"pageEnum":1,"url":"http://www.risultati-ammissione.polimi.it/2022_20040_html/2022_20040_generale.html"},"course":null},{"phase":"Anticipato","school":"Design","year":2022,"url":{"pageEnum":1,"url":"http://www.risultati-ammissione.polimi.it/2022_20040_html/2022_20040_generale.html"},"course":null},{"phase":"Anticipato","school":"Design","year":2022,"url":{"pageEnum":1,"url":"http://www.risultati-ammissione.polimi.it\\2022_20040_html\\2022_20040_generale.html"},"course":null},{"phase":"Anticipato","school":"Design","year":2022,"url":{"pageEnum":1,"url":"http://www.risultati-ammissione.polimi.it\\2022_20040_html\\2022_20040_generale.html"},"course":null}],"inMeritTable":true}}