{"9919dc2de379d53f04a8":{"id":"9919dc2de379d53f04a8","singleCourseJsons":[{"phase":"Prima Graduatoria Di Seconda Fase","school":"Ingegneria","year":2022,"url":{"pageEnum":1,"url":"http://www.risultati-ammissione.polimi.it/2022_20064_html/2022_20064_generale.html"},"course":"INGEGNERIA GESTIONALE"},{"phase":"Prima Graduatoria Di Seconda Fase","school":"Ingegneria","year":2022,"url":{"pageEnum":1,"url":"http://www.risultati-ammissione.polimi.it\\2022_20064_html\\2022_20064_generale.html"},"course":"INGEGNERIA GESTIONALE"}],"rankingSummaries":[{"phase":"Prima Graduatoria Di Seconda Fase","school":"Ingegneria","year":2022,"url":{"pageEnum":1,"url":"http://www.risultati-ammissione.polimi.it/2022_20064_html/2022_20064_generale.html"},"course":null},{"phase":"Prima Graduatoria Di Seconda Fase","school":"Ingegneria","year":2022,"url":{"pageEnum":1,"url":"http://www.risultati-ammissione.polimi.it/2022_20064_html/2022_20064_generale.html"},"course":null},{"phase":"Prima Graduatoria Di Seconda Fase","school":"Ingegneria","year":2022,"url":{"pageEnum":1,"url":"http://www.risultati-ammissione.polimi.it\\2022_20064_html\\2022_20064_generale.html"},"course":null},{"phase":"Prima Graduatoria Di Seconda Fase","school":"Ingegneria","year":2022,"url":{"pageEnum":1,"url":"http://www.risultati-ammissione.polimi.it\\2022_20064_html\\2022_20064_generale.html"},"course":null}],"inMeritTable":true},"9919aa0a429fec2c648f":{"id":"9919aa0a429fec2c648f","singleCourseJsons":[{"phase":"Standard","school":"Design","year":2021,"url":{"pageEnum":1,"url":"http://www.risultati-ammissione.polimi.it/2021_20041_html/2021_20041_generale.html"},"course":"DESIGN DEGLI INTERNI"},{"phase":"Standard","school":"Design","year":2021,"url":{"pageEnum":1,"url":"http://www.risultati-ammissione.polimi.it\\2021_20041_html\\2021_20041_generale.html"},"course":"DESIGN DEGLI INTERNI"}],"rankingSummaries":[{"phase":"Standard","school":"Design","year":2021,"url":{"pageEnum":1,"url":"http://www.risultati-ammissione.polimi.it/2021_20041_html/2021_20041_generale.html"},"course":null},{"phase":"Standard","school":"Design","year":2021,"url":{"pageEnum":1,"url":"http://www.risultati-ammissione.polimi.it/2021_20041_html/2021_20041_generale.html"},"course":null},{"phase":"Standard","school":"Design","year":2021,"url":{"pageEnum":1,"url":"http://www.risultati-ammissione.polimi.it\\2021_20041_html\\2021_20041_generale.html"},"course":null},{"phase":"Standard","school":"Design","year":2021,"url":{"pageEnum":1,"url":"http://www.risultati-ammissione.polimi.it\\2021_20041_html\\2021_20041_generale.html"},"course":null}],"inMeritTable":true}}