{"a41b74efbcec90ad1d74":{"id":"a41b74efbcec90ad1d74","singleCourseJsons":[{"phase":"Extra-ue","school":"Architettura","year":2021,"url":{"pageEnum":1,"url":"http://www.risultati-ammissione.polimi.it/2021_20005_html/2021_20005_generale.html"},"course":"PROGETTAZIONE DELL'ARCHITETTURA - TAUGHT IN ENGLISH"},{"phase":"Extra-ue","school":"Architettura","year":2021,"url":{"pageEnum":1,"url":"http://www.risultati-ammissione.polimi.it/2021_20005_html/2021_20005_generale.html"},"course":"PROGETTAZIONE DELL'ARCHITETTURA - TAUGHT IN ENGLISH"},{"phase":"Extra-ue Seconda Graduatoria","school":"Architettura","year":2021,"url":{"pageEnum":1,"url":"http://www.risultati-ammissione.polimi.it/2021_20104_html/2021_20104_generale.html"},"course":"PROGETTAZIONE DELL'ARCHITETTURA - TAUGHT IN ENGLISH"},{"phase":"Extra-ue Seconda Graduatoria","school":"Architettura","year":2021,"url":{"pageEnum":1,"url":"http://www.risultati-ammissione.polimi.it/2021_20104_html/2021_20104_generale.html"},"course":"PROGETTAZIONE DELL'ARCHITETTURA - TAUGHT IN ENGLISH"},{"phase":"Extra-ue","school":"Architettura","year":2021,"url":{"pageEnum":1,"url":"http://www.risultati-ammissione.polimi.it\\2021_20005_html\\2021_20005_generale.html"},"course":"PROGETTAZIONE DELL'ARCHITETTURA - TAUGHT IN ENGLISH"},{"phase":"Extra-ue","school":"Architettura","year":2021,"url":{"pageEnum":1,"url":"http://www.risultati-ammissione.polimi.it\\2021_20005_html\\2021_20005_generale.html"},"course":"PROGETTAZIONE DELL'ARCHITETTURA - TAUGHT IN ENGLISH"},{"phase":"Extra-ue Seconda Graduatoria","school":"Architettura","year":2021,"url":{"pageEnum":1,"url":"http://www.risultati-ammissione.polimi.it\\2021_20104_html\\2021_20104_generale.html"},"course":"PROGETTAZIONE DELL'ARCHITETTURA - TAUGHT IN ENGLISH"},{"phase":"Extra-ue Seconda Graduatoria","school":"Architettura","year":2021,"url":{"pageEnum":1,"url":"http://www.risultati-ammissione.polimi.it\\2021_20104_html\\2021_20104_generale.html"},"course":"PROGETTAZIONE DELL'ARCHITETTURA - TAUGHT IN ENGLISH"}],"rankingSummaries":[{"phase":"Extra-ue","school":"Architettura","year":2021,"url":{"pageEnum":1,"url":"http://www.risultati-ammissione.polimi.it/2021_20005_html/2021_20005_generale.html"},"course":null},{"phase":"Extra-ue","school":"Architettura","year":2021,"url":{"pageEnum":1,"url":"http://www.risultati-ammissione.polimi.it/2021_20005_html/2021_20005_generale.html"},"course":null},{"phase":"Extra-ue","school":"Architettura","year":2021,"url":{"pageEnum":1,"url":"http://www.risultati-ammissione.polimi.it/2021_20005_html/2021_20005_generale.html"},"course":null},{"phase":"Extra-ue Seconda Graduatoria","school":"Architettura","year":2021,"url":{"pageEnum":1,"url":"http://www.risultati-ammissione.polimi.it/2021_20104_html/2021_20104_generale.html"},"course":null},{"phase":"Extra-ue Seconda Graduatoria","school":"Architettura","year":2021,"url":{"pageEnum":1,"url":"http://www.risultati-ammissione.polimi.it/2021_20104_html/2021_20104_generale.html"},"course":null},{"phase":"Extra-ue Seconda Graduatoria","school":"Architettura","year":2021,"url":{"pageEnum":1,"url":"http://www.risultati-ammissione.polimi.it/2021_20104_html/2021_20104_generale.html"},"course":null},{"phase":"Extra-ue","school":"Architettura","year":2021,"url":{"pageEnum":1,"url":"http://www.risultati-ammissione.polimi.it\\2021_20005_html\\2021_20005_generale.html"},"course":null},{"phase":"Extra-ue","school":"Architettura","year":2021,"url":{"pageEnum":1,"url":"http://www.risultati-ammissione.polimi.it\\2021_20005_html\\2021_20005_generale.html"},"course":null},{"phase":"Extra-ue","school":"Architettura","year":2021,"url":{"pageEnum":1,"url":"http://www.risultati-ammissione.polimi.it\\2021_20005_html\\2021_20005_generale.html"},"course":null},{"phase":"Extra-ue Seconda Graduatoria","school":"Architettura","year":2021,"url":{"pageEnum":1,"url":"http://www.risultati-ammissione.polimi.it\\2021_20104_html\\2021_20104_generale.html"},"course":null},{"phase":"Extra-ue Seconda Graduatoria","school":"Architettura","year":2021,"url":{"pageEnum":1,"url":"http://www.risultati-ammissione.polimi.it\\2021_20104_html\\2021_20104_generale.html"},"course":null},{"phase":"Extra-ue Seconda Graduatoria","school":"Architettura","year":2021,"url":{"pageEnum":1,"url":"http://www.risultati-ammissione.polimi.it\\2021_20104_html\\2021_20104_generale.html"},"course":null}],"inMeritTable":true},"a41bc1bd096d2201c40d":{"id":"a41bc1bd096d2201c40d","singleCourseJsons":[{"phase":"Anticipato","school":"Design","year":2023,"url":{"pageEnum":1,"url":"http://www.risultati-ammissione.polimi.it/2023_20040_32ea_html/2023_20040_generale.html"},"course":"DESIGN DEGLI INTERNI"},{"phase":"Anticipato","school":"Design","year":2023,"url":{"pageEnum":1,"url":"http://www.risultati-ammissione.polimi.it/2023_20040_32ea_html/2023_20040_generale.html"},"course":"DESIGN DEL PRODOTTO INDUSTRIALE"},{"phase":"Anticipato","school":"Design","year":2023,"url":{"pageEnum":1,"url":"http://www.risultati-ammissione.polimi.it/2023_20040_32ea_html/2023_20040_generale.html"},"course":"DESIGN DELLA COMUNICAZIONE"},{"phase":"Anticipato","school":"Design","year":2023,"url":{"pageEnum":1,"url":"http://www.risultati-ammissione.polimi.it/2023_20040_32ea_html/2023_20040_generale.html"},"course":"DESIGN DELLA MODA"},{"phase":"Anticipato","school":"Design","year":2023,"url":{"pageEnum":1,"url":"http://www.risultati-ammissione.polimi.it\\2023_20040_32ea_html\\2023_20040_generale.html"},"course":"DESIGN DEGLI INTERNI"},{"phase":"Anticipato","school":"Design","year":2023,"url":{"pageEnum":1,"url":"http://www.risultati-ammissione.polimi.it\\2023_20040_32ea_html\\2023_20040_generale.html"},"course":"DESIGN DEL PRODOTTO INDUSTRIALE"},{"phase":"Anticipato","school":"Design","year":2023,"url":{"pageEnum":1,"url":"http://www.risultati-ammissione.polimi.it\\2023_20040_32ea_html\\2023_20040_generale.html"},"course":"DESIGN DELLA COMUNICAZIONE"},{"phase":"Anticipato","school":"Design","year":2023,"url":{"pageEnum":1,"url":"http://www.risultati-ammissione.polimi.it\\2023_20040_32ea_html\\2023_20040_generale.html"},"course":"DESIGN DELLA MODA"}],"rankingSummaries":[{"phase":"Anticipato","school":"Design","year":2023,"url":{"pageEnum":1,"url":"http://www.risultati-ammissione.polimi.it/2023_20040_32ea_html/2023_20040_generale.html"},"course":null},{"phase":"Anticipato","school":"Design","year":2023,"url":{"pageEnum":1,"url":"http://www.risultati-ammissione.polimi.it/2023_20040_32ea_html/2023_20040_generale.html"},"course":null},{"phase":"Anticipato","school":"Design","year":2023,"url":{"pageEnum":1,"url":"http://www.risultati-ammissione.polimi.it/2023_20040_32ea_html/2023_20040_generale.html"},"course":null},{"phase":"Anticipato","school":"Design","year":2023,"url":{"pageEnum":1,"url":"http://www.risultati-ammissione.polimi.it/2023_20040_32ea_html/2023_20040_generale.html"},"course":null},{"phase":"Anticipato","school":"Design","year":2023,"url":{"pageEnum":1,"url":"http://www.risultati-ammissione.polimi.it/2023_20040_32ea_html/2023_20040_generale.html"},"course":null},{"phase":"Anticipato","school":"Design","year":2023,"url":{"pageEnum":1,"url":"http://www.risultati-ammissione.polimi.it\\2023_20040_32ea_html\\2023_20040_generale.html"},"course":null},{"phase":"Anticipato","school":"Design","year":2023,"url":{"pageEnum":1,"url":"http://www.risultati-ammissione.polimi.it\\2023_20040_32ea_html\\2023_20040_generale.html"},"course":null},{"phase":"Anticipato","school":"Design","year":2023,"url":{"pageEnum":1,"url":"http://www.risultati-ammissione.polimi.it\\2023_20040_32ea_html\\2023_20040_generale.html"},"course":null},{"phase":"Anticipato","school":"Design","year":2023,"url":{"pageEnum":1,"url":"http://www.risultati-ammissione.polimi.it\\2023_20040_32ea_html\\2023_20040_generale.html"},"course":null},{"phase":"Anticipato","school":"Design","year":2023,"url":{"pageEnum":1,"url":"http://www.risultati-ammissione.polimi.it\\2023_20040_32ea_html\\2023_20040_generale.html"},"course":null}],"inMeritTable":true}}