{"d0e0b6d38f19ab7331d1":{"id":"d0e0b6d38f19ab7331d1","singleCourseJsons":[{"phase":"Prima Graduatoria Di Seconda Fase","school":"Ingegneria","year":2021,"url":{"pageEnum":1,"url":"http://www.risultati-ammissione.polimi.it/2021_20064_html/2021_20064_generale.html"},"course":"INGEGNERIA BIOMEDICA"},{"phase":"Prima Graduatoria Di Seconda Fase","school":"Ingegneria","year":2021,"url":{"pageEnum":1,"url":"http://www.risultati-ammissione.polimi.it/2021_20064_html/2021_20064_generale.html"},"course":"INGEGNERIA DEI MATERIALI E DELLE NANOTECNOLOGIE"},{"phase":"Prima Graduatoria Di Seconda Fase","school":"Ingegneria","year":2021,"url":{"pageEnum":1,"url":"http://www.risultati-ammissione.polimi.it\\2021_20064_html\\2021_20064_generale.html"},"course":"INGEGNERIA BIOMEDICA"},{"phase":"Prima Graduatoria Di Seconda Fase","school":"Ingegneria","year":2021,"url":{"pageEnum":1,"url":"http://www.risultati-ammissione.polimi.it\\2021_20064_html\\2021_20064_generale.html"},"course":"INGEGNERIA DEI MATERIALI E DELLE NANOTECNOLOGIE"}],"rankingSummaries":[{"phase":"Prima Graduatoria Di Seconda Fase","school":"Ingegneria","year":2021,"url":{"pageEnum":1,"url":"http://www.risultati-ammissione.polimi.it/2021_20064_html/2021_20064_generale.html"},"course":null},{"phase":"Prima Graduatoria Di Seconda Fase","school":"Ingegneria","year":2021,"url":{"pageEnum":1,"url":"http://www.risultati-ammissione.polimi.it/2021_20064_html/2021_20064_generale.html"},"course":null},{"phase":"Prima Graduatoria Di Seconda Fase","school":"Ingegneria","year":2021,"url":{"pageEnum":1,"url":"http://www.risultati-ammissione.polimi.it/2021_20064_html/2021_20064_generale.html"},"course":null},{"phase":"Prima Graduatoria Di Seconda Fase","school":"Ingegneria","year":2021,"url":{"pageEnum":1,"url":"http://www.risultati-ammissione.polimi.it\\2021_20064_html\\2021_20064_generale.html"},"course":null},{"phase":"Prima Graduatoria Di Seconda Fase","school":"Ingegneria","year":2021,"url":{"pageEnum":1,"url":"http://www.risultati-ammissione.polimi.it\\2021_20064_html\\2021_20064_generale.html"},"course":null},{"phase":"Prima Graduatoria Di Seconda Fase","school":"Ingegneria","year":2021,"url":{"pageEnum":1,"url":"http://www.risultati-ammissione.polimi.it\\2021_20064_html\\2021_20064_generale.html"},"course":null}],"inMeritTable":true},"d0e0f6edefa40bcb4f7c":{"id":"d0e0f6edefa40bcb4f7c","singleCourseJsons":[{"phase":"Standard","school":"Design","year":2021,"url":{"pageEnum":1,"url":"http://www.risultati-ammissione.polimi.it/2021_20041_html/2021_20041_generale.html"},"course":"DESIGN DEGLI INTERNI"},{"phase":"Standard","school":"Design","year":2021,"url":{"pageEnum":1,"url":"http://www.risultati-ammissione.polimi.it/2021_20041_html/2021_20041_generale.html"},"course":"DESIGN DELLA COMUNICAZIONE"},{"phase":"Standard","school":"Design","year":2021,"url":{"pageEnum":1,"url":"http://www.risultati-ammissione.polimi.it\\2021_20041_html\\2021_20041_generale.html"},"course":"DESIGN DEGLI INTERNI"},{"phase":"Standard","school":"Design","year":2021,"url":{"pageEnum":1,"url":"http://www.risultati-ammissione.polimi.it\\2021_20041_html\\2021_20041_generale.html"},"course":"DESIGN DELLA COMUNICAZIONE"}],"rankingSummaries":[{"phase":"Standard","school":"Design","year":2021,"url":{"pageEnum":1,"url":"http://www.risultati-ammissione.polimi.it/2021_20041_html/2021_20041_generale.html"},"course":null},{"phase":"Standard","school":"Design","year":2021,"url":{"pageEnum":1,"url":"http://www.risultati-ammissione.polimi.it/2021_20041_html/2021_20041_generale.html"},"course":null},{"phase":"Standard","school":"Design","year":2021,"url":{"pageEnum":1,"url":"http://www.risultati-ammissione.polimi.it/2021_20041_html/2021_20041_generale.html"},"course":null},{"phase":"Standard","school":"Design","year":2021,"url":{"pageEnum":1,"url":"http://www.risultati-ammissione.polimi.it\\2021_20041_html\\2021_20041_generale.html"},"course":null},{"phase":"Standard","school":"Design","year":2021,"url":{"pageEnum":1,"url":"http://www.risultati-ammissione.polimi.it\\2021_20041_html\\2021_20041_generale.html"},"course":null},{"phase":"Standard","school":"Design","year":2021,"url":{"pageEnum":1,"url":"http://www.risultati-ammissione.polimi.it\\2021_20041_html\\2021_20041_generale.html"},"course":null}],"inMeritTable":true}}