{"e07291409b93c4d34e10":{"id":"e07291409b93c4d34e10","singleCourseJsons":[{"phase":"Prima Graduatoria Di Seconda Fase","school":"Ingegneria","year":2021,"url":{"pageEnum":1,"url":"http://www.risultati-ammissione.polimi.it/2021_20064_html/2021_20064_generale.html"},"course":"INGEGNERIA GESTIONALE"},{"phase":"Prima Graduatoria Di Seconda Fase","school":"Ingegneria","year":2021,"url":{"pageEnum":1,"url":"http://www.risultati-ammissione.polimi.it\\2021_20064_html\\2021_20064_generale.html"},"course":"INGEGNERIA GESTIONALE"}],"rankingSummaries":[{"phase":"Prima Graduatoria Di Seconda Fase","school":"Ingegneria","year":2021,"url":{"pageEnum":1,"url":"http://www.risultati-ammissione.polimi.it/2021_20064_html/2021_20064_generale.html"},"course":null},{"phase":"Prima Graduatoria Di Seconda Fase","school":"Ingegneria","year":2021,"url":{"pageEnum":1,"url":"http://www.risultati-ammissione.polimi.it/2021_20064_html/2021_20064_generale.html"},"course":null},{"phase":"Prima Graduatoria Di Seconda Fase","school":"Ingegneria","year":2021,"url":{"pageEnum":1,"url":"http://www.risultati-ammissione.polimi.it\\2021_20064_html\\2021_20064_generale.html"},"course":null},{"phase":"Prima Graduatoria Di Seconda Fase","school":"Ingegneria","year":2021,"url":{"pageEnum":1,"url":"http://www.risultati-ammissione.polimi.it\\2021_20064_html\\2021_20064_generale.html"},"course":null}],"inMeritTable":true},"e0728c8e0223c96ebea1":{"id":"e0728c8e0223c96ebea1","singleCourseJsons":[{"phase":"Prima Graduatoria","school":"Architettura","year":2022,"url":{"pageEnum":1,"url":"http://www.risultati-ammissione.polimi.it/2022_20002_46h3_html/2022_20002_generale.html"},"course":"PROGETTAZIONE DELL'ARCHITETTURA"},{"phase":"Prima Graduatoria","school":"Architettura","year":2022,"url":{"pageEnum":1,"url":"http://www.risultati-ammissione.polimi.it\\2022_20002_46h3_html\\2022_20002_generale.html"},"course":"PROGETTAZIONE DELL'ARCHITETTURA"}],"rankingSummaries":[{"phase":"Prima Graduatoria","school":"Architettura","year":2022,"url":{"pageEnum":1,"url":"http://www.risultati-ammissione.polimi.it/2022_20002_46h3_html/2022_20002_generale.html"},"course":null},{"phase":"Prima Graduatoria","school":"Architettura","year":2022,"url":{"pageEnum":1,"url":"http://www.risultati-ammissione.polimi.it/2022_20002_46h3_html/2022_20002_generale.html"},"course":null},{"phase":"Prima Graduatoria","school":"Architettura","year":2022,"url":{"pageEnum":1,"url":"http://www.risultati-ammissione.polimi.it\\2022_20002_46h3_html\\2022_20002_generale.html"},"course":null},{"phase":"Prima Graduatoria","school":"Architettura","year":2022,"url":{"pageEnum":1,"url":"http://www.risultati-ammissione.polimi.it\\2022_20002_46h3_html\\2022_20002_generale.html"},"course":null}],"inMeritTable":true}}